Classfile ./original/build/classes/java/main/LombokDataClass$LombokDataClassBuilder.class
  Last modified Dec 24, 2024; size 2187 bytes
  SHA-256 checksum 682b251879ef783223995eebdd2689ba6b3bf4d02a7d2bdfa0ca01c2bec91bab
  Compiled from "LombokDataClass.java"
public class LombokDataClass$LombokDataClassBuilder
  minor version: 0
  major version: 67
  flags: (0x0021) ACC_PUBLIC, ACC_SUPER
  this_class: #8                          // LombokDataClass$LombokDataClassBuilder
  super_class: #2                         // java/lang/Object
  interfaces: 0, fields: 4, methods: 7, attributes: 5
Constant pool:
   #1 = Methodref          #2.#3          // java/lang/Object."<init>":()V
   #2 = Class              #4             // java/lang/Object
   #3 = NameAndType        #5:#6          // "<init>":()V
   #4 = Utf8               java/lang/Object
   #5 = Utf8               <init>
   #6 = Utf8               ()V
   #7 = Fieldref           #8.#9          // LombokDataClass$LombokDataClassBuilder.a:I
   #8 = Class              #10            // LombokDataClass$LombokDataClassBuilder
   #9 = NameAndType        #11:#12        // a:I
  #10 = Utf8               LombokDataClass$LombokDataClassBuilder
  #11 = Utf8               a
  #12 = Utf8               I
  #13 = Class              #14            // java/lang/NullPointerException
  #14 = Utf8               java/lang/NullPointerException
  #15 = String             #16            // b is marked non-null but is null
  #16 = Utf8               b is marked non-null but is null
  #17 = Methodref          #13.#18        // java/lang/NullPointerException."<init>":(Ljava/lang/String;)V
  #18 = NameAndType        #5:#19         // "<init>":(Ljava/lang/String;)V
  #19 = Utf8               (Ljava/lang/String;)V
  #20 = Fieldref           #8.#21         // LombokDataClass$LombokDataClassBuilder.b:Ljava/lang/String;
  #21 = NameAndType        #22:#23        // b:Ljava/lang/String;
  #22 = Utf8               b
  #23 = Utf8               Ljava/lang/String;
  #24 = Fieldref           #8.#25         // LombokDataClass$LombokDataClassBuilder.c:I
  #25 = NameAndType        #26:#12        // c:I
  #26 = Utf8               c
  #27 = Fieldref           #8.#28         // LombokDataClass$LombokDataClassBuilder.d:Ljava/lang/String;
  #28 = NameAndType        #29:#23        // d:Ljava/lang/String;
  #29 = Utf8               d
  #30 = Class              #31            // LombokDataClass
  #31 = Utf8               LombokDataClass
  #32 = Methodref          #30.#33        // LombokDataClass."<init>":(ILjava/lang/String;ILjava/lang/String;)V
  #33 = NameAndType        #5:#34         // "<init>":(ILjava/lang/String;ILjava/lang/String;)V
  #34 = Utf8               (ILjava/lang/String;ILjava/lang/String;)V
  #35 = InvokeDynamic      #0:#36         // #0:makeConcatWithConstants:(ILjava/lang/String;ILjava/lang/String;)Ljava/lang/String;
  #36 = NameAndType        #37:#38        // makeConcatWithConstants:(ILjava/lang/String;ILjava/lang/String;)Ljava/lang/String;
  #37 = Utf8               makeConcatWithConstants
  #38 = Utf8               (ILjava/lang/String;ILjava/lang/String;)Ljava/lang/String;
  #39 = Utf8               RuntimeInvisibleAnnotations
  #40 = Utf8               Llombok/Generated;
  #41 = Utf8               Code
  #42 = Utf8               LineNumberTable
  #43 = Utf8               LocalVariableTable
  #44 = Utf8               this
  #45 = Utf8               LLombokDataClass$LombokDataClassBuilder;
  #46 = Utf8               (I)LLombokDataClass$LombokDataClassBuilder;
  #47 = Utf8               (Ljava/lang/String;)LLombokDataClass$LombokDataClassBuilder;
  #48 = Utf8               StackMapTable
  #49 = Utf8               RuntimeInvisibleParameterAnnotations
  #50 = Utf8               Lorg/jetbrains/annotations/NotNull;
  #51 = Utf8               Lorg/jetbrains/annotations/Nullable;
  #52 = Utf8               build
  #53 = Utf8               ()LLombokDataClass;
  #54 = Utf8               toString
  #55 = Utf8               ()Ljava/lang/String;
  #56 = Utf8               SourceFile
  #57 = Utf8               LombokDataClass.java
  #58 = Utf8               NestHost
  #59 = Utf8               BootstrapMethods
  #60 = String             #61            // LombokDataClass.LombokDataClassBuilder(a=\u0001, b=\u0001, c=\u0001, d=\u0001)
  #61 = Utf8               LombokDataClass.LombokDataClassBuilder(a=\u0001, b=\u0001, c=\u0001, d=\u0001)
  #62 = MethodHandle       6:#63          // REF_invokeStatic java/lang/invoke/StringConcatFactory.makeConcatWithConstants:(Ljava/lang/invoke/MethodHandles$Lookup;Ljava/lang/String;Ljava/lang/invoke/MethodType;Ljava/lang/String;[Ljava/lang/Object;)Ljava/lang/invoke/CallSite;
  #63 = Methodref          #64.#65        // java/lang/invoke/StringConcatFactory.makeConcatWithConstants:(Ljava/lang/invoke/MethodHandles$Lookup;Ljava/lang/String;Ljava/lang/invoke/MethodType;Ljava/lang/String;[Ljava/lang/Object;)Ljava/lang/invoke/CallSite;
  #64 = Class              #66            // java/lang/invoke/StringConcatFactory
  #65 = NameAndType        #37:#67        // makeConcatWithConstants:(Ljava/lang/invoke/MethodHandles$Lookup;Ljava/lang/String;Ljava/lang/invoke/MethodType;Ljava/lang/String;[Ljava/lang/Object;)Ljava/lang/invoke/CallSite;
  #66 = Utf8               java/lang/invoke/StringConcatFactory
  #67 = Utf8               (Ljava/lang/invoke/MethodHandles$Lookup;Ljava/lang/String;Ljava/lang/invoke/MethodType;Ljava/lang/String;[Ljava/lang/Object;)Ljava/lang/invoke/CallSite;
  #68 = Utf8               InnerClasses
  #69 = Utf8               LombokDataClassBuilder
  #70 = Class              #71            // java/lang/invoke/MethodHandles$Lookup
  #71 = Utf8               java/lang/invoke/MethodHandles$Lookup
  #72 = Class              #73            // java/lang/invoke/MethodHandles
  #73 = Utf8               java/lang/invoke/MethodHandles
  #74 = Utf8               Lookup
{
  private int a;
    descriptor: I
    flags: (0x0002) ACC_PRIVATE
    RuntimeInvisibleAnnotations:
      0: #40()
        lombok.Generated

  private java.lang.String b;
    descriptor: Ljava/lang/String;
    flags: (0x0002) ACC_PRIVATE
    RuntimeInvisibleAnnotations:
      0: #40()
        lombok.Generated

  private int c;
    descriptor: I
    flags: (0x0002) ACC_PRIVATE
    RuntimeInvisibleAnnotations:
      0: #40()
        lombok.Generated

  private java.lang.String d;
    descriptor: Ljava/lang/String;
    flags: (0x0002) ACC_PRIVATE
    RuntimeInvisibleAnnotations:
      0: #40()
        lombok.Generated

  LombokDataClass$LombokDataClassBuilder();
    descriptor: ()V
    flags: (0x0000)
    Code:
      stack=1, locals=1, args_size=1
         0: aload_0
         1: invokespecial #1                  // Method java/lang/Object."<init>":()V
         4: return
      LineNumberTable:
        line 7: 0
      LocalVariableTable:
        Start  Length  Slot  Name   Signature
            0       5     0  this   LLombokDataClass$LombokDataClassBuilder;
    RuntimeInvisibleAnnotations:
      0: #40()
        lombok.Generated

  public LombokDataClass$LombokDataClassBuilder a(int);
    descriptor: (I)LLombokDataClass$LombokDataClassBuilder;
    flags: (0x0001) ACC_PUBLIC
    Code:
      stack=2, locals=2, args_size=2
         0: aload_0
         1: iload_1
         2: putfield      #7                  // Field a:I
         5: aload_0
         6: areturn
      LineNumberTable:
        line 7: 0
      LocalVariableTable:
        Start  Length  Slot  Name   Signature
            0       7     0  this   LLombokDataClass$LombokDataClassBuilder;
            0       7     1     a   I
    RuntimeInvisibleAnnotations:
      0: #40()
        lombok.Generated

  public LombokDataClass$LombokDataClassBuilder b(java.lang.String);
    descriptor: (Ljava/lang/String;)LLombokDataClass$LombokDataClassBuilder;
    flags: (0x0001) ACC_PUBLIC
    Code:
      stack=3, locals=2, args_size=2
         0: aload_1
         1: ifnonnull     14
         4: new           #13                 // class java/lang/NullPointerException
         7: dup
         8: ldc           #15                 // String b is marked non-null but is null
        10: invokespecial #17                 // Method java/lang/NullPointerException."<init>":(Ljava/lang/String;)V
        13: athrow
        14: aload_0
        15: aload_1
        16: putfield      #20                 // Field b:Ljava/lang/String;
        19: aload_0
        20: areturn
      LineNumberTable:
        line 7: 0
      LocalVariableTable:
        Start  Length  Slot  Name   Signature
            0      21     0  this   LLombokDataClass$LombokDataClassBuilder;
            0      21     1     b   Ljava/lang/String;
      StackMapTable: number_of_entries = 1
        frame_type = 14 /* same */
    RuntimeInvisibleAnnotations:
      0: #40()
        lombok.Generated
    RuntimeInvisibleParameterAnnotations:
      parameter 0:
        0: #50()
          org.jetbrains.annotations.NotNull

  public LombokDataClass$LombokDataClassBuilder c(int);
    descriptor: (I)LLombokDataClass$LombokDataClassBuilder;
    flags: (0x0001) ACC_PUBLIC
    Code:
      stack=2, locals=2, args_size=2
         0: aload_0
         1: iload_1
         2: putfield      #24                 // Field c:I
         5: aload_0
         6: areturn
      LineNumberTable:
        line 7: 0
      LocalVariableTable:
        Start  Length  Slot  Name   Signature
            0       7     0  this   LLombokDataClass$LombokDataClassBuilder;
            0       7     1     c   I
    RuntimeInvisibleAnnotations:
      0: #40()
        lombok.Generated

  public LombokDataClass$LombokDataClassBuilder d(java.lang.String);
    descriptor: (Ljava/lang/String;)LLombokDataClass$LombokDataClassBuilder;
    flags: (0x0001) ACC_PUBLIC
    Code:
      stack=2, locals=2, args_size=2
         0: aload_0
         1: aload_1
         2: putfield      #27                 // Field d:Ljava/lang/String;
         5: aload_0
         6: areturn
      LineNumberTable:
        line 7: 0
      LocalVariableTable:
        Start  Length  Slot  Name   Signature
            0       7     0  this   LLombokDataClass$LombokDataClassBuilder;
            0       7     1     d   Ljava/lang/String;
    RuntimeInvisibleAnnotations:
      0: #40()
        lombok.Generated
    RuntimeInvisibleParameterAnnotations:
      parameter 0:
        0: #51()
          org.jetbrains.annotations.Nullable

  public LombokDataClass build();
    descriptor: ()LLombokDataClass;
    flags: (0x0001) ACC_PUBLIC
    Code:
      stack=6, locals=1, args_size=1
         0: new           #30                 // class LombokDataClass
         3: dup
         4: aload_0
         5: getfield      #7                  // Field a:I
         8: aload_0
         9: getfield      #20                 // Field b:Ljava/lang/String;
        12: aload_0
        13: getfield      #24                 // Field c:I
        16: aload_0
        17: getfield      #27                 // Field d:Ljava/lang/String;
        20: invokespecial #32                 // Method LombokDataClass."<init>":(ILjava/lang/String;ILjava/lang/String;)V
        23: areturn
      LineNumberTable:
        line 7: 0
      LocalVariableTable:
        Start  Length  Slot  Name   Signature
            0      24     0  this   LLombokDataClass$LombokDataClassBuilder;
    RuntimeInvisibleAnnotations:
      0: #40()
        lombok.Generated

  public java.lang.String toString();
    descriptor: ()Ljava/lang/String;
    flags: (0x0001) ACC_PUBLIC
    Code:
      stack=4, locals=1, args_size=1
         0: aload_0
         1: getfield      #7                  // Field a:I
         4: aload_0
         5: getfield      #20                 // Field b:Ljava/lang/String;
         8: aload_0
         9: getfield      #24                 // Field c:I
        12: aload_0
        13: getfield      #27                 // Field d:Ljava/lang/String;
        16: invokedynamic #35,  0             // InvokeDynamic #0:makeConcatWithConstants:(ILjava/lang/String;ILjava/lang/String;)Ljava/lang/String;
        21: areturn
      LineNumberTable:
        line 7: 0
      LocalVariableTable:
        Start  Length  Slot  Name   Signature
            0      22     0  this   LLombokDataClass$LombokDataClassBuilder;
    RuntimeInvisibleAnnotations:
      0: #40()
        lombok.Generated
}
SourceFile: "LombokDataClass.java"
RuntimeInvisibleAnnotations:
  0: #40()
    lombok.Generated
NestHost: class LombokDataClass
BootstrapMethods:
  0: #62 REF_invokeStatic java/lang/invoke/StringConcatFactory.makeConcatWithConstants:(Ljava/lang/invoke/MethodHandles$Lookup;Ljava/lang/String;Ljava/lang/invoke/MethodType;Ljava/lang/String;[Ljava/lang/Object;)Ljava/lang/invoke/CallSite;
    Method arguments:
      #60 LombokDataClass.LombokDataClassBuilder(a=\u0001, b=\u0001, c=\u0001, d=\u0001)
InnerClasses:
  public static #69= #8 of #30;           // LombokDataClassBuilder=class LombokDataClass$LombokDataClassBuilder of class LombokDataClass
  public static final #74= #70 of #72;    // Lookup=class java/lang/invoke/MethodHandles$Lookup of class java/lang/invoke/MethodHandles
